text_extensions/__init__.py
text_extensions/_data.py
text_extensions/py.typed
text_extensions-1.0.1.dist-info/METADATA
text_extensions-1.0.1.dist-info/WHEEL
text_extensions-1.0.1.dist-info/licenses/LICENSE
text_extensions-1.0.1.dist-info/RECORD
