Metadata-Version: 2.4
Name: text-extensions
Version: 1.0.1
Summary: Check if a file or extension is text, and iterate over 300+ known text file types including source code, markup, data formats, and configuration files. Python port of text-extensions npm package.
Project-URL: Homepage, https://github.com/ysskrishna/text-extensions
Project-URL: Repository, https://github.com/ysskrishna/text-extensions.git
Project-URL: Issues, https://github.com/ysskrishna/text-extensions/issues
Project-URL: Changelog, https://github.com/ysskrishna/text-extensions/blob/main/CHANGELOG.md
Project-URL: Discussions, https://github.com/ysskrishna/text-extensions/discussions
Author-email: ysskrishna <sivasaikrishnassk@gmail.com>
License: MIT
License-File: LICENSE
Keywords: ascii,extension,extensions,file,file-detection,file-extensions,file-type,file-utils,mime-type,mit license,source-code,text,text-detection,text-files,utilities,utils,ysskrishna
Classifier: Development Status :: 5 - Production/Stable
Classifier: Intended Audience :: Developers
Classifier: License :: OSI Approved :: MIT License
Classifier: Operating System :: OS Independent
Classifier: Programming Language :: Python :: 3
Classifier: Programming Language :: Python :: 3.8
Classifier: Programming Language :: Python :: 3.9
Classifier: Programming Language :: Python :: 3.10
Classifier: Programming Language :: Python :: 3.11
Classifier: Programming Language :: Python :: 3.12
Classifier: Topic :: Software Development :: Libraries :: Python Modules
Classifier: Topic :: Text Processing
Classifier: Typing :: Typed
Requires-Python: >=3.8
